geniac/__init__.py
geniac/cli/__init__.py
geniac/cli/__main__.py
geniac/cli/commands/__init__.py
geniac/cli/commands/base.py
geniac/cli/commands/clean.py
geniac/cli/commands/configs.py
geniac/cli/commands/init.py
geniac/cli/commands/install.py
geniac/cli/commands/lint.py
geniac/cli/commands/options.py
geniac/cli/commands/recipes.py
geniac/cli/commands/test.py
geniac/cli/data/conf/geniac.ini
geniac/cli/data/conf/logging.json
geniac/cli/data/scripts/geniac.bash
geniac/cli/parsers/__init__.py
geniac/cli/parsers/base.py
geniac/cli/parsers/config.py
geniac/cli/parsers/scripts.py
geniac/cli/utils/__init__.py
geniac/cli/utils/base.py
geniac/cli/utils/errorcounter.py
geniac/cli/utils/logging.py
geniac/cmake/CMakeLists.txt
geniac/cmake/FindApptainer.cmake
geniac/cmake/FindDocker.cmake
geniac/cmake/FindNextflow.cmake
geniac/cmake/FindPodman.cmake
geniac/cmake/FindSingularity.cmake
geniac/cmake/checkConfigFiles.cmake
geniac/cmake/createPathDirectories.cmake
geniac/cmake/createWorkDir.cmake
geniac/cmake/functionColorMessage.cmake
geniac/cmake/initCmakePreload.sh
geniac/cmake/stepAddTestTargets.cmake
geniac/cmake/stepCheckOptions.cmake
geniac/cmake/stepFindPackages.cmake
geniac/cmake/stepGitInfo.cmake
geniac/cmake/stepMainCoreScript.cmake
geniac/cmake/stepSetVariables.cmake
geniac/install/cmake-init-default.cmake
geniac/install/docker.nf
geniac/install/nextflow.config.in
geniac/install/singularity.nf
geniac/repo/CMakeLists.txt
geniac/repo/setup.py
geniac/repo/tox.ini
geniac/repo/cmake/CMakeLists.txt
geniac/repo/cmake/FindApptainer.cmake
geniac/repo/cmake/FindDocker.cmake
geniac/repo/cmake/FindNextflow.cmake
geniac/repo/cmake/FindPodman.cmake
geniac/repo/cmake/FindSingularity.cmake
geniac/repo/cmake/checkConfigFiles.cmake
geniac/repo/cmake/createPathDirectories.cmake
geniac/repo/cmake/createWorkDir.cmake
geniac/repo/cmake/functionColorMessage.cmake
geniac/repo/cmake/initCmakePreload.sh
geniac/repo/cmake/stepAddTestTargets.cmake
geniac/repo/cmake/stepCheckOptions.cmake
geniac-3.7.0.dist-info/licenses/LICENSE
geniac-3.7.0.dist-info/METADATA
geniac-3.7.0.dist-info/WHEEL
geniac-3.7.0.dist-info/entry_points.txt
geniac-3.7.0.dist-info/top_level.txt
geniac-3.7.0.dist-info/RECORD
