Metadata-Version: 2.4
Name: geniac
Version: 3.7.0
Summary: Automatic Configuration GENerator and Installer for nextflow pipeline
Home-page: https://gitlab.curie.fr/bioinfo-guidelines/geniac
Author: Philippe Hupé, Julien Roméjon, Fabrice Allain
Author-email: philippe.hupe@curie.fr
License: CeCILL
Project-URL: Documentation, https://geniac.readthedocs.io/en/latest/
Project-URL: Demonstration, https://github.com/bioinfo-pf-curie/geniac-demo.git
Platform: any
Classifier: Development Status :: 4 - Beta
Classifier: Programming Language :: Python
Classifier: Programming Language :: Python :: 3.12
Requires-Python: >=3.12
License-File: LICENSE
Requires-Dist: cmake==3.30.2
Requires-Dist: colorlog==6.8.2
Requires-Dist: dotty-dict==1.3.1
Requires-Dist: gitpython==3.1.43
Requires-Dist: pre-commit==3.8.0
Requires-Dist: pytest==8.3.2
Requires-Dist: pytest-cov==5.0.0
Requires-Dist: pytest-datadir==1.5.0
Requires-Dist: pytest-datafiles==3.0.0
Requires-Dist: pytest-icdiff==0.9
Requires-Dist: pytest-sugar==1.0.0
Requires-Dist: pyyaml==6.0.2
Requires-Dist: setuptools-scm==8.1.0
Requires-Dist: tox==3.28.0
Requires-Dist: tox-conda==0.10.2
Requires-Dist: validators==0.33.0
Provides-Extra: testing
Requires-Dist: setuptools; extra == "testing"
Requires-Dist: pytest; extra == "testing"
Requires-Dist: pytest-cov; extra == "testing"
Requires-Dist: pytest-sugar; extra == "testing"
Requires-Dist: pytest-icdiff; extra == "testing"
Requires-Dist: pytest-datafiles; extra == "testing"
Dynamic: license-file
